pryvx_ml/__init__.py
pryvx_ml/fl_client.py
pryvx_ml-1.4.1.dist-info/LICENSE
pryvx_ml-1.4.1.dist-info/METADATA
pryvx_ml-1.4.1.dist-info/WHEEL
pryvx_ml-1.4.1.dist-info/top_level.txt
pryvx_ml-1.4.1.dist-info/RECORD
