Metadata-Version: 2.1
Name: pryvx-ml
Version: 1.4.1
Summary: Federated Learning python library
Home-page: UNKNOWN
Author: PryvX (Jayesh Kenaudekar)
Author-email: <jayesh@pryvx.com>
License: MIT
Keywords: python,privacy-preserving,federated-learning,machine-learning
Platform: UNKNOWN
Classifier: Programming Language :: Python :: 3.9
Classifier: Intended Audience :: Developers
Classifier: License :: OSI Approved :: MIT License
Classifier: Operating System :: OS Independent
License-File: LICENSE
Requires-Dist: numpy
Requires-Dist: scikit-learn
Requires-Dist: requests
